{
    "boxShadow": "none",
    "widgetName": "InventoryAddSku",
    "isFilterable": true,
    "dynamicPropertyPathList": [{"key": "sourceData"}],
    "iconSVG": "https://appcdn.appsmith.com/static/media/icon.a7b19dc8b31d68fcff57f1d2c0084a18.svg",
    "displayName": "Select",
    "labelText": "SKU",
    "topRow": 0,
    "searchTags": ["dropdown"],
    "bottomRow": 6.6,
    "parentRowSpace": 10,
    "labelWidth": 5,
    "type": "SELECT_WIDGET",
    "serverSideFiltering": false,
    "hideCard": false,
    "defaultOptionValue": "{{ ((options, serverSideFiltering) => ( SKUEntry.text))(InventoryAddSku.options, InventoryAddSku.serverSideFiltering) }}",
    "animateLoading": true,
    "parentColumnSpace": 5.0625,
    "dynamicTriggerPathList": [],
    "leftColumn": 0,
    "dynamicBindingPathList": [
        {"key": "accentColor"},
        {"key": "borderRadius"},
        {"key": "sourceData"},
        {"key": "defaultOptionValue"}
    ],
    "labelPosition": "Top",
    "placeholderText": "Select option",
    "isDisabled": false,
    "sourceData": "{{QueryTop1kInventory.data.map( (obj) =>{ return  {'SKU': obj.SKU, 'PartName': obj.PartName } })}}",
    "key": "4ng9dmaaoe",
    "labelTextSize": "0.875rem",
    "isRequired": false,
    "isDeprecated": false,
    "rightColumn": 32,
    "dynamicHeight": "FIXED",
    "accentColor": "{{appsmith.theme.colors.primaryColor}}",
    "widgetId": "en4rrdjaci",
    "optionValue": "SKU",
    "minWidth": 450,
    "isVisible": true,
    "version": 1,
    "parentId": "ol8yolymow",
    "tags": [
        "Suggested",
        "Select"
    ],
    "isLoading": false,
    "labelAlignment": "left",
    "renderMode": "CANVAS",
    "optionLabel": "SKU",
    "borderRadius": "{{appsmith.theme.borderRadius.appBorderRadius}}",
    "maxDynamicHeight": 9000,
    "minDynamicHeight": 4
}