{
    "boxShadow": "none",
    "widgetName": "ModalChangePassword",
    "isCanvas": true,
    "displayName": "Modal",
    "iconSVG": "https://appcdn.appsmith.com/static/media/icon.b374721fa8e1aeab7cf326c2d865506f.svg",
    "searchTags": [
        "dialog",
        "popup",
        "notification"
    ],
    "topRow": 31.196875,
    "bottomRow": 377.1968749999854,
    "parentRowSpace": 10,
    "type": "MODAL_WIDGET",
    "hideCard": false,
    "shouldScrollContents": true,
    "animateLoading": true,
    "parentColumnSpace": 16.109375,
    "dynamicTriggerPathList": [{"key": "onClose"}],
    "leftColumn": 20,
    "dynamicBindingPathList": [{"key": "borderRadius"}],
    "children": [{
        "boxShadow": "{{appsmith.theme.boxShadow.appBoxShadow}}",
        "mobileBottomRow": 240,
        "widgetName": "Canvas8",
        "displayName": "Canvas",
        "topRow": 0,
        "bottomRow": 340,
        "parentRowSpace": 1,
        "type": "CANVAS_WIDGET",
        "canExtend": true,
        "hideCard": true,
        "shouldScrollContents": false,
        "minHeight": 348.0000000000001,
        "mobileRightColumn": 64,
        "useAutoLayout": false,
        "parentColumnSpace": 1,
        "leftColumn": 0,
        "dynamicBindingPathList": [
            {"key": "borderRadius"},
            {"key": "boxShadow"}
        ],
        "positioning": "fixed",
        "isDisabled": false,
        "key": "7lf06f72t4",
        "isDeprecated": false,
        "rightColumn": 64,
        "detachFromLayout": true,
        "dynamicHeight": "AUTO_HEIGHT",
        "widgetId": "apyvtknwfh",
        "minWidth": 450,
        "isVisible": true,
        "version": 1,
        "parentId": "winn2qr20q",
        "renderMode": "CANVAS",
        "isLoading": false,
        "mobileTopRow": 0,
        "layout": [{
            "layout": [
                {
                    "layout": [
                        {
                            "layout": [{
                                "widgetId": "s3z9nkr9er",
                                "alignment": "start"
                            }],
                            "isPermanent": true,
                            "allowedWidgetTypes": ["TEXT_WIDGET"],
                            "layoutType": "WIDGET_ROW",
                            "layoutStyle": {
                                "minHeight": "40px",
                                "flexGrow": 1
                            },
                            "layoutId": "njgsnlljdy",
                            "isDropTarget": true
                        },
                        {
                            "layout": [{
                                "widgetId": "lghalcdhlm",
                                "alignment": "start"
                            }],
                            "isPermanent": true,
                            "allowedWidgetTypes": ["ICON_BUTTON_WIDGET"],
                            "layoutType": "WIDGET_ROW",
                            "layoutStyle": {
                                "minHeight": "40px",
                                "minWidth": "30px"
                            },
                            "layoutId": "b3ph34eddu",
                            "isDropTarget": true
                        }
                    ],
                    "isPermanent": true,
                    "layoutType": "LAYOUT_ROW",
                    "layoutStyle": {"minHeight": "40px"},
                    "layoutId": "5mc75af8u1"
                },
                {
                    "layout": [],
                    "isPermanent": true,
                    "layoutType": "ALIGNED_LAYOUT_COLUMN",
                    "layoutStyle": {
                        "minHeight": "40px",
                        "width": "100%"
                    },
                    "layoutId": "1q06gke09v",
                    "isDropTarget": true
                },
                {
                    "layout": [
                        {
                            "widgetId": "0jkphs7zwk",
                            "alignment": "end"
                        },
                        {
                            "widgetId": "ay530rchnc",
                            "alignment": "end"
                        }
                    ],
                    "isPermanent": true,
                    "layoutType": "ALIGNED_WIDGET_ROW",
                    "layoutStyle": {"minHeight": "40px"},
                    "layoutId": "4dyso61jvk",
                    "isDropTarget": true
                }
            ],
            "isPermanent": true,
            "layoutType": "LAYOUT_COLUMN",
            "layoutId": "j16gtkhjsf"
        }],
        "borderRadius": "{{appsmith.theme.borderRadius.appBorderRadius}}",
        "mobileLeftColumn": 0,
        "maxDynamicHeight": 9000,
        "minDynamicHeight": 4
    }],
    "key": "lzo5nbmtss",
    "height": 345.99999999998545,
    "isDeprecated": false,
    "rightColumn": 44,
    "detachFromLayout": true,
    "dynamicHeight": "AUTO_HEIGHT",
    "widgetId": "winn2qr20q",
    "canOutsideClickClose": true,
    "canEscapeKeyClose": true,
    "version": 2,
    "parentId": "0",
    "tags": ["Layout"],
    "renderMode": "CANVAS",
    "isLoading": false,
    "onClose": "{{resetWidget(\"ModalChangePassword\", true);}}",
    "borderRadius": "{{appsmith.theme.borderRadius.appBorderRadius}}",
    "maxDynamicHeight": 9000,
    "width": 456,
    "minDynamicHeight": 8
}