{
  "gitSyncId": "666b27d34105bf614fd3798d_82f8696a-c900-4ed5-b901-b5ea3b873d8c",
  "id": "Module Tracking_SelectLast5PcbSolderModules",
  "pluginId": "mssql-plugin",
  "pluginType": "DB",
  "unpublishedAction": {
    "actionConfiguration": {
      "body": "SELECT TOP 5 * FROM dbo.ModuleTracker WHERE (CurrentStatus = 'Soldered') ORDER BY ID DESC",
      "encodeParamsToggle": true,
      "paginationType": "NONE",
      "pluginSpecifiedTemplates": [
        {
          "value": true
        }
      ],
      "timeoutInMillisecond": 10000
    },
    "confirmBeforeExecute": false,
    "datasource": {
      "id": "TE-ModuleTracking-Azure",
      "isAutoGenerated": false,
      "name": "TE-ModuleTracking-Azure",
      "pluginId": "mssql-plugin"
    },
    "dynamicBindingPathList": [],
    "executeOnLoad": true,
    "name": "SelectLast5PcbSolderModules",
    "pageId": "Module Tracking",
    "userSetOnLoad": false
  }
}