{
  "accentColor": "{{appsmith.theme.colors.primaryColor}}",
  "animateLoading": true,
  "borderRadius": "{{appsmith.theme.borderRadius.appBorderRadius}}",
  "bottomRow": 30,
  "boxShadow": "none",
  "defaultOptionValue": "PRODUCTION",
  "displayName": "Select",
  "dynamicBindingPathList": [
    {
      "key": "accentColor"
    },
    {
      "key": "borderRadius"
    }
  ],
  "dynamicHeight": "FIXED",
  "dynamicPropertyPathList": [
    {
      "key": "sourceData"
    }
  ],
  "dynamicTriggerPathList": [],
  "hideCard": false,
  "iconSVG": "https://appcdn.appsmith.com/static/media/icon.a7b19dc8b31d68fcff57f1d2c0084a18.svg",
  "isDeprecated": false,
  "isDisabled": false,
  "isFilterable": false,
  "isLoading": false,
  "isRequired": true,
  "isVisible": true,
  "key": "1y2txopke6",
  "labelAlignment": "left",
  "labelPosition": "Top",
  "labelText": "Department",
  "labelTextSize": "0.875rem",
  "labelWidth": 5,
  "leftColumn": 0,
  "maxDynamicHeight": 9000,
  "minDynamicHeight": 4,
  "minWidth": 450,
  "optionLabel": "Label",
  "optionValue": "Value",
  "parentColumnSpace": 6.6875,
  "parentId": "jdezyb6aq1",
  "parentRowSpace": 10,
  "placeholderText": "Select option",
  "renderMode": "CANVAS",
  "rightColumn": 32,
  "searchTags": [
    "dropdown"
  ],
  "serverSideFiltering": false,
  "sourceData": "[\n  {\n    \"Label\": \"Production\",\n    \"Value\": \"PRODUCTION\"\n  },\n  {\n    \"Label\": \"Management\",\n    \"Value\": \"MANAGEMENT\"\n  }\n]",
  "tags": [
    "Suggested",
    "Select"
  ],
  "topRow": 23,
  "type": "SELECT_WIDGET",
  "version": 1,
  "widgetId": "45ch726pfu",
  "widgetName": "NewEmpDept"
}