{
    "boxShadow": "{{appsmith.theme.boxShadow.appBoxShadow}}",
    "widgetName": "Container2",
    "borderColor": "#E0DEDE",
    "isCanvas": true,
    "displayName": "Container",
    "iconSVG": "https://appcdn.appsmith.com/static/media/icon.daebf68875b6c8e909e9e8ac8bee0c02.svg",
    "searchTags": [
        "div",
        "parent",
        "group"
    ],
    "topRow": 26,
    "bottomRow": 46,
    "parentRowSpace": 10,
    "type": "CONTAINER_WIDGET",
    "hideCard": false,
    "shouldScrollContents": true,
    "animateLoading": true,
    "parentColumnSpace": 6.96875,
    "dynamicTriggerPathList": [],
    "leftColumn": 0,
    "dynamicBindingPathList": [
        {"key": "borderRadius"},
        {"key": "boxShadow"}
    ],
    "children": [{
        "boxShadow": "{{appsmith.theme.boxShadow.appBoxShadow}}",
        "mobileBottomRow": 100,
        "widgetName": "Canvas3",
        "displayName": "Canvas",
        "topRow": 0,
        "bottomRow": 200,
        "parentRowSpace": 1,
        "type": "CANVAS_WIDGET",
        "canExtend": false,
        "hideCard": true,
        "minHeight": 100,
        "mobileRightColumn": 64,
        "parentColumnSpace": 1,
        "leftColumn": 0,
        "dynamicBindingPathList": [
            {"key": "borderRadius"},
            {"key": "boxShadow"}
        ],
        "key": "lahyia47kq",
        "isDeprecated": false,
        "rightColumn": 64,
        "detachFromLayout": true,
        "dynamicHeight": "AUTO_HEIGHT",
        "widgetId": "24mnf0v0tw",
        "containerStyle": "none",
        "minWidth": 450,
        "isVisible": true,
        "version": 1,
        "parentId": "fg4eszly9g",
        "renderMode": "CANVAS",
        "isLoading": false,
        "mobileTopRow": 0,
        "responsiveBehavior": "fill",
        "borderRadius": "{{appsmith.theme.borderRadius.appBorderRadius}}",
        "mobileLeftColumn": 0,
        "maxDynamicHeight": 9000,
        "minDynamicHeight": 4,
        "flexLayers": [
            {"children": [{
                "id": "ke8ir6aeb7",
                "align": "start"
            }]},
            {"children": [{
                "id": "69yavv0m6j",
                "align": "start"
            }]},
            {"children": [{
                "id": "bmhtppmga1",
                "align": "start"
            }]}
        ]
    }],
    "borderWidth": "0\n",
    "key": "z3flcf5a75",
    "backgroundColor": "#FFFFFF",
    "isDeprecated": false,
    "rightColumn": 64,
    "dynamicHeight": "AUTO_HEIGHT",
    "widgetId": "fg4eszly9g",
    "containerStyle": "card",
    "minWidth": 450,
    "isVisible": true,
    "version": 1,
    "parentId": "ysv9ghtrs5",
    "tags": ["Layout"],
    "renderMode": "CANVAS",
    "isLoading": false,
    "originalTopRow": 26,
    "borderRadius": "{{appsmith.theme.borderRadius.appBorderRadius}}",
    "maxDynamicHeight": 9000,
    "originalBottomRow": 46,
    "minDynamicHeight": 10
}