{
  "gitSyncId": "666b27d34105bf614fd3798d_c3b4c945-927c-4ce2-809e-37553bb36822",
  "id": "Module Tracking__$JSCurrentTime$_JSCurrentTime.getNow",
  "isPublic": true,
  "moduleInstanceId": "Module Tracking_JSCurrentTime",
  "pluginId": "js-plugin",
  "pluginType": "JS",
  "rootModuleInstanceId": "Module Tracking_JSCurrentTime",
  "unpublishedAction": {
    "collectionId": "Module Tracking__$JSCurrentTime$_JSCurrentTime",
    "confirmBeforeExecute": false,
    "contextType": "PAGE",
    "datasource": {
      "isAutoGenerated": false,
      "name": "UNUSED_DATASOURCE",
      "pluginId": "js-plugin"
    },
    "executeOnLoad": false,
    "fullyQualifiedName": "_$JSCurrentTime$_JSCurrentTime.getNow",
    "name": "getNow",
    "pageId": "Module Tracking",
    "userSetOnLoad": false
  }
}